phasty/__init__.py
phasty/parser.py
phasty/wrapper.py
phasty-0.5.3.dist-info/LICENSE
phasty-0.5.3.dist-info/METADATA
phasty-0.5.3.dist-info/WHEEL
phasty-0.5.3.dist-info/top_level.txt
phasty-0.5.3.dist-info/RECORD
