Metadata-Version: 2.1
Name: phasty
Version: 0.5.3
Summary: A Python interface for PHAST (phylogenetic analysis with space/time models).
Home-page: https://github.com/yuanx749/phasty
Author: Xiao Yuan
Author-email: yuanx749@gmail.com
License: BSD 3-Clause License
Keywords: phylogenetics
Classifier: Programming Language :: Python :: 3
Classifier: License :: OSI Approved :: BSD License
Classifier: Operating System :: OS Independent
Requires-Python: >=3.8
License-File: LICENSE
Requires-Dist: numpy
Provides-Extra: dev
Requires-Dist: pre-commit ; extra == 'dev'
Requires-Dist: black ==22.3.0 ; extra == 'dev'
Requires-Dist: flake8 ==4.0.1 ; extra == 'dev'
Requires-Dist: isort ==5.12.0 ; extra == 'dev'
Requires-Dist: pytest ; extra == 'dev'
Requires-Dist: pytest-cov ; extra == 'dev'
Provides-Extra: doc
Requires-Dist: sphinx ==7.2.6 ; extra == 'doc'
Requires-Dist: furo ==2023.9.10 ; extra == 'doc'
Requires-Dist: myst-parser ==2.0.0 ; extra == 'doc'
Requires-Dist: sphinx-copybutton ==0.5.2 ; extra == 'doc'
